scripts/__init__.py
scripts/actions.py
scripts/checkstyle-all.jar
scripts/checkstyle-config.xml
scripts/config.py
scripts/hbt.py
scripts/hbt2.py
scripts/pipeline.py
scripts/sourcefile.py
scripts/test_hbt.py
scripts/test_hbt2.py
hbt-5.0.4.dist-info/LICENSE.txt
hbt-5.0.4.dist-info/METADATA
hbt-5.0.4.dist-info/WHEEL
hbt-5.0.4.dist-info/entry_points.txt
hbt-5.0.4.dist-info/top_level.txt
hbt-5.0.4.dist-info/RECORD
